jrn/__init__.py
jrn/_dist_ver.py
j_rn-0.2.1.dist-info/LICENCE
j_rn-0.2.1.dist-info/METADATA
j_rn-0.2.1.dist-info/WHEEL
j_rn-0.2.1.dist-info/top_level.txt
j_rn-0.2.1.dist-info/RECORD
